pluginlib/__init__.py
pluginlib/_loader.py
pluginlib/_objects.py
pluginlib/_parent.py
pluginlib/_util.py
pluginlib/exceptions.py
pluginlib-0.10.0.dist-info/licenses/LICENSE
pluginlib-0.10.0.dist-info/METADATA
pluginlib-0.10.0.dist-info/WHEEL
pluginlib-0.10.0.dist-info/top_level.txt
pluginlib-0.10.0.dist-info/RECORD
